{"data": [{"id": 3515514, "wikiDataId": "Q4117373", "name": "Al Mamzar", "country": "United Arab Emirates", "countryCode": "AE", "region": "Emirate of Dubai", "regionCode": "DU", "regionWdId": "Q613", "latitude": 25.309469444, "longitude": 55.342811111, "population": 0}, {"id": 3386644, "wikiDataId": "Q3694483", "name": "Ab Band District", "country": "Afghanistan", "countryCode": "AF", "region": "Ghazni", "regionCode": "GHA", "regionWdId": "Q180415", "latitude": 32.983, "longitude": 67.967, "population": 0}, {"id": 3339608, "wikiDataId": "Q2572213", "name": "Ab Kamari", "country": "Afghanistan", "countryCode": "AF", "region": "Badghis", "regionCode": "BDG", "regionWdId": "Q172052", "latitude": 34.925, "longitude": 62.901666666, "population": 0}, {"id": 3228129, "wikiDataId": "Q1650529", "name": "Achin", "country": "Afghanistan", "countryCode": "AF", "region": "Nangarhar", "regionCode": "NAN", "regionWdId": "Q178471", "latitude": 34.0894, "longitude": 70.683, "population": 0}, {"id": 3301438, "wikiDataId": "Q2714271", "name": "Adraskan District", "country": "Afghanistan", "countryCode": "AF", "region": "Herat Province", "regionCode": "HER", "regionWdId": "Q182844", "latitude": 33.705277777, "longitude": 61.995555555, "population": 0}, {"id": 3198316, "wikiDataId": "Q3918406", "name": "Ahmadabad District", "country": "Afghanistan", "countryCode": "AF", "region": "Paktia Zurmat", "regionCode": "PIA", "regionWdId": "Q182493", "latitude": 33.773888888, "longitude": 69.339722222, "population": 0}, {"id": 3223788, "wikiDataId": "Q2674014", "name": "Ajristan District", "country": "Afghanistan", "countryCode": "AF", "region": "Ghazni", "regionCode": "GHA", "regionWdId": "Q180415", "latitude": 33.466962, "longitude": 67.238846, "population": 0}, {"id": 3382471, "wikiDataId": "Q2830672", "name": "Alasay", "country": "Afghanistan", "countryCode": "AF", "region": "Kapisa", "regionCode": "KAP", "regionWdId": "Q173816", "latitude": 34.925555555, "longitude": 69.809166666, "population": 0}, {"id": 3347217, "wikiDataId": "Q2123756", "name": "Ali Abad", "country": "Afghanistan", "countryCode": "AF", "region": "Kunduz", "regionCode": "KDZ", "regionWdId": "Q186418", "latitude": 36.53, "longitude": 68.877777777, "population": 0}, {"id": 3348637, "wikiDataId": "Q1229725", "name": "Alingar", "country": "Afghanistan", "countryCode": "AF", "region": "Laghman", "regionCode": "LAG", "regionWdId": "Q185442", "latitude": 34.8347, "longitude": 70.3603, "population": 0}], "links": [{"rel": "first", "href": "/v1/geo/adminDivisions?offset=0&limit=10"}, {"rel": "next", "href": "/v1/geo/adminDivisions?offset=10&limit=10"}, {"rel": "last", "href": "/v1/geo/adminDivisions?offset=55550&limit=10"}], "metadata": {"currentOffset": 0, "totalCount": 55551}}